tensorparser
