Metadata-Version: 1.0
Name: tensorparser
Version: 0.12
Summary: Generate code from tensor expressions
Home-page: https://github.com/tlamadon/tensorparser
Author: Thibaut Lamadon
Author-email: thibaut.lamadon@gmail.com
License: MIT
Platform: UNKNOWN
